{
  "main": {
    "id": "b74c8ae3d3dbc1a5",
    "type": "split",
    "children": [
      {
        "id": "f019486903a3d3c5",
        "type": "tabs",
        "children": [
          {
            "id": "0a41d0330af2eec0",
            "type": "leaf",
            "state": {
              "type": "markdown",
              "state": {
                "file": "math/Set theory/Basic Logical Operations.md",
                "mode": "source",
                "source": false
              },
              "icon": "lucide-file",
              "title": "Basic Logical Operations"
            }
          }
        ]
      }
    ],
    "direction": "vertical"
  },
  "left": {
    "id": "de7403c1b23cc99a",
    "type": "split",
    "children": [
      {
        "id": "5ce0fef538390501",
        "type": "tabs",
        "children": [
          {
            "id": "648c52eb879f938e",
            "type": "leaf",
            "state": {
              "type": "file-explorer",
              "state": {
                "sortOrder": "alphabetical"
              },
              "icon": "lucide-folder-closed",
              "title": "파일 탐색기"
            }
          },
          {
            "id": "23b6e5bf385e53d4",
            "type": "leaf",
            "state": {
              "type": "search",
              "state": {
                "query": "",
                "matchingCase": false,
                "explainSearch": false,
                "collapseAll": false,
                "extraContext": false,
                "sortOrder": "alphabetical"
              },
              "icon": "lucide-search",
              "title": "검색"
            }
          },
          {
            "id": "aefcc26c264e7974",
            "type": "leaf",
            "state": {
              "type": "bookmarks",
              "state": {},
              "icon": "lucide-bookmark",
              "title": "Bookmarks"
            }
          }
        ]
      }
    ],
    "direction": "horizontal",
    "width": 300
  },
  "right": {
    "id": "98b252e769283f49",
    "type": "split",
    "children": [
      {
        "id": "83355acf2dd560e4",
        "type": "tabs",
        "children": [
          {
            "id": "50c6f55be20da1ed",
            "type": "leaf",
            "state": {
              "type": "backlink",
              "state": {
                "collapseAll": false,
                "extraContext": false,
                "sortOrder": "alphabetical",
                "showSearch": false,
                "searchQuery": "",
                "backlinkCollapsed": false,
                "unlinkedCollapsed": true
              },
              "icon": "links-coming-in",
              "title": "백링크"
            }
          },
          {
            "id": "c4b9e7534fa15c5a",
            "type": "leaf",
            "state": {
              "type": "outgoing-link",
              "state": {
                "linksCollapsed": false,
                "unlinkedCollapsed": true
              },
              "icon": "links-going-out",
              "title": "나가는 링크"
            }
          },
          {
            "id": "7de0038f20b5edc6",
            "type": "leaf",
            "state": {
              "type": "tag",
              "state": {
                "sortOrder": "frequency",
                "useHierarchy": true
              },
              "icon": "lucide-tags",
              "title": "Tags"
            }
          },
          {
            "id": "f6f62323f51fae3d",
            "type": "leaf",
            "state": {
              "type": "outline",
              "state": {
                "file": "math/Topology/Interval.md"
              },
              "icon": "lucide-list",
              "title": "Interval 개요"
            }
          }
        ]
      }
    ],
    "direction": "horizontal",
    "width": 300,
    "collapsed": true
  },
  "left-ribbon": {
    "hiddenItems": {
      "switcher:퀵 스위처 열기": false,
      "graph:그래프 뷰 열기": false,
      "canvas:새 캔버스 만들기": false,
      "daily-notes:오늘의 데일리 노트 열기": false,
      "templates:템플릿 삽입": false,
      "command-palette:명령어 팔레트 열기": false
    }
  },
  "active": "0a41d0330af2eec0",
  "lastOpenFiles": [
    "math/Set theory/Proposition.md",
    "math/Set theory/Set.md",
    "math/Set theory/Basic Logical Operations.md",
    "math/Set theory",
    "math/Topology",
    "math/Topology/Interval.md",
    "math",
    "Welcome.md"
  ]
}